setup.py
lete_probability_distributions/Binomialdistribution.py
lete_probability_distributions/Gaussiandistribution.py
lete_probability_distributions/Generaldistribution.py
lete_probability_distributions/__init__.py
lete_probability_distributions.egg-info/PKG-INFO
lete_probability_distributions.egg-info/SOURCES.txt
lete_probability_distributions.egg-info/dependency_links.txt
lete_probability_distributions.egg-info/not-zip-safe
lete_probability_distributions.egg-info/top_level.txt