Metadata-Version: 1.0
Name: lete-probability-distributions
Version: 1.1
Summary: Gaussian and Binomial distributions
Home-page: UNKNOWN
Author: UNKNOWN
Author-email: lete.nwibasi@gmail.com
License: UNKNOWN
Platform: UNKNOWN
